{
    "url": "https://github.com/jcmkk3/trochilidae/tree/main/berylline",
    "layouts": {
        "LAYOUT": {
            "layout": [
                {"x": 0, "y": 1.165, "w": 1.059, "r": -8, "rx": 0.529, "ry": 1.665},
                {"x": 1.161, "y": 0.317, "w": 1.059, "r": -3, "rx": 1.691, "ry": 0.817},
                {"x": 2.342, "y": 0, "w": 1.059},
                {"x": 3.43, "y": 0.257, "w": 1.059},
                {"x": 4.518, "y": 0.772, "w": 1.059},
                {"x": 7.482, "y": 0.772, "w": 1.059},
                {"x": 8.57, "y": 0.257, "w": 1.059},
                {"x": 9.658, "y": 0, "w": 1.059},
                {"x": 10.839, "y": 0.317, "w": 1.059, "r": 3, "rx": 11.369, "ry": 0.817},
                {"x": 12, "y": 1.165, "w": 1.059, "r": 8, "rx": 12.53, "ry": 1.665},
                {"x": 0.143, "y": 2.184, "w": 1.059, "r": -8, "rx": 0.672, "ry": 2.684},
                {"x": 1.215, "y": 1.345, "w": 1.059, "r": -3, "rx": 1.744, "ry": 1.845},
                {"x": 2.342, "y": 1.029, "w": 1.059},
                {"x": 3.43, "y": 1.287, "w": 1.059},
                {"x": 4.518, "y": 1.801, "w": 1.059},
                {"x": 7.482, "y": 1.801, "w": 1.059},
                {"x": 8.57, "y": 1.287, "w": 1.059},
                {"x": 9.658, "y": 1.029, "w": 1.059},
                {"x": 10.785, "y": 1.345, "w": 1.059, "r": 3, "rx": 11.315, "ry": 1.845},
                {"x": 11.857, "y": 2.184, "w": 1.059, "r": 8, "rx": 12.386, "ry": 2.684},
                {"x": 1.269, "y": 2.373, "w": 1.059, "r": -3, "rx": 1.798, "ry": 2.873},
                {"x": 2.342, "y": 2.059, "w": 1.059},
                {"x": 3.43, "y": 2.316, "w": 1.059},
                {"x": 8.57, "y": 2.316, "w": 1.059},
                {"x": 9.658, "y": 2.059, "w": 1.059},
                {"x": 10.731, "y": 2.373, "w": 1.059, "r": 3, "rx": 11.261, "ry": 2.873},
                {"x": 3.702, "y": 3.61, "w": 1.059},
                {"x": 4.79, "y": 3.868, "w": 1.059},
                {"x": 7.21, "y": 3.868, "w": 1.059},
                {"x": 8.298, "y": 3.61, "w": 1.059}
            ]
        }
    }
}
